hachiko_bapu/FluidSynth.py
hachiko_bapu/__init__.py
hachiko_bapu/funutils.py
hachiko_bapu/hachi.py
hachiko_bapu/hachitools.py
hachiko_bapu/instrument.sf2
hachiko_bapu/synthesize.py
hachiko_bapu/cli_tools/__init__.py
hachiko_bapu/cli_tools/lrc_merge.py
hachiko_bapu/cli_tools/srt2mid.py
hachiko_bapu-0.1.8.dist-info/LICENSE
hachiko_bapu-0.1.8.dist-info/METADATA
hachiko_bapu-0.1.8.dist-info/WHEEL
hachiko_bapu-0.1.8.dist-info/entry_points.txt
hachiko_bapu-0.1.8.dist-info/top_level.txt
hachiko_bapu-0.1.8.dist-info/RECORD
